pycoda/__init__.py
pycoda/codafile.py
pycoda/factories.py
pycoda/fields.py
pycoda/records.py
codapy-0.3.28.dist-info/LICENSE.txt
codapy-0.3.28.dist-info/METADATA
codapy-0.3.28.dist-info/WHEEL
codapy-0.3.28.dist-info/top_level.txt
codapy-0.3.28.dist-info/zip-safe
codapy-0.3.28.dist-info/RECORD
